jonga/__init__.py
bald_jonga-0.1.1.dist-info/METADATA
bald_jonga-0.1.1.dist-info/WHEEL
bald_jonga-0.1.1.dist-info/top_level.txt
bald_jonga-0.1.1.dist-info/RECORD
