Metadata-Version: 2.1
Name: bald-jonga
Version: 0.1.1
Summary: A Python library that intercepts print statements automatically.
Author: Mateus Elias
Author-email: meap@cin.ufpe.br
Classifier: Programming Language :: Python :: 3
Classifier: License :: OSI Approved :: MIT License
Classifier: Operating System :: OS Independent
Requires-Python: >=3.6
